textile/__init__.py
textile/__main__.py
textile/core.py
textile/regex_strings.py
textile/textilefactory.py
textile/utils.py
textile/version.py
textile/objects/__init__.py
textile/objects/block.py
textile/objects/table.py
textile-4.0.3.dist-info/LICENSE.txt
textile-4.0.3.dist-info/METADATA
textile-4.0.3.dist-info/WHEEL
textile-4.0.3.dist-info/entry_points.txt
textile-4.0.3.dist-info/top_level.txt
textile-4.0.3.dist-info/RECORD
