Metadata-Version: 2.1
Name: textile
Version: 4.0.3
Summary: Textile processing for python.
Author-email: Dennis Burke <ikirudennis@gmail.com>
Project-URL: Homepage, https://github.com/textile/python-textile
Project-URL: Repository, https://github.com/textile/python-textile.git
Project-URL: Issues, https://github.com/textile/python-textile/issues
Keywords: textile,text,html markup
Classifier: Development Status :: 5 - Production/Stable
Classifier: Environment :: Web Environment
Classifier: Intended Audience :: Developers
Classifier: License :: OSI Approved :: BSD License
Classifier: Operating System :: OS Independent
Classifier: Programming Language :: Python
Classifier: Programming Language :: Python :: 3
Classifier: Programming Language :: Python :: 3 :: Only
Classifier: Programming Language :: Python :: 3.8
Classifier: Programming Language :: Python :: 3.9
Classifier: Programming Language :: Python :: 3.10
Classifier: Programming Language :: Python :: 3.11
Classifier: Programming Language :: Python :: 3.12
Classifier: Topic :: Software Development :: Libraries :: Python Modules
Requires-Python: >=3.8
License-File: LICENSE.txt
Requires-Dist: nh3
Requires-Dist: regex>1.0; implementation_name != "pypy"
Provides-Extra: develop
Requires-Dist: pytest; extra == "develop"
Requires-Dist: pytest-cov; extra == "develop"
Provides-Extra: imagesize
Requires-Dist: Pillow>=3.0.0; extra == "imagesize"
